README.rst
appveyor_artifacts.py
setup.py
appveyor_artifacts.egg-info/PKG-INFO
appveyor_artifacts.egg-info/SOURCES.txt
appveyor_artifacts.egg-info/dependency_links.txt
appveyor_artifacts.egg-info/entry_points.txt
appveyor_artifacts.egg-info/requires.txt
appveyor_artifacts.egg-info/top_level.txt
appveyor_artifacts.egg-info/zip-safe