Metadata-Version: 1.1
Name: appveyor-artifacts
Version: 1.0.2
Summary: Download artifacts from AppVeyor builds of the same commit/pull request.
Home-page: https://github.com/Robpol86/appveyor-artifacts
Author: @Robpol86
Author-email: robpol86@gmail.com
License: MIT
Keywords: appveyor artifacts travis coverage coveralls
Platform: UNKNOWN
Classifier: Development Status :: 5 - Production/Stable
Classifier: Environment :: Console
Classifier: Environment :: MacOS X
Classifier: Intended Audience :: Developers
Classifier: License :: OSI Approved :: MIT License
Classifier: Operating System :: MacOS :: MacOS X
Classifier: Operating System :: POSIX
Classifier: Operating System :: POSIX :: Linux
Classifier: Programming Language :: Python :: 2.7
Classifier: Programming Language :: Python :: 3.3
Classifier: Programming Language :: Python :: 3.4
Classifier: Programming Language :: Python :: 3.5
Classifier: Programming Language :: Python :: Implementation :: PyPy
Classifier: Topic :: Terminals
